[
    {
		"title": "Elysian Island",
		"notes": "Gang: Son Of Legacy (SOL)",
		"order": 0,
		"strokecolor": "FF0000",
		"fillcolor": "FF0000",
		"latlngarray": [
			{"lat": -76.962, "lng": -28.355},
			{"lat": -76.962, "lng": -22.957},
			{"lat": -78.425, "lng": -22.957},
			{"lat": -78.425, "lng": -0.351},
			{"lat": -80.331, "lng": -0.351},
			{"lat": -80.331, "lng": 5.081},
			{"lat": -83.151, "lng": 5.081},
			{"lat": -83.151, "lng": -12.716},
			{"lat": -80.639, "lng": -12.716},
			{"lat": -80.639, "lng": -28.359},
			{"lat": -81.408, "lng": -28.359},
			{"lat": -81.408, "lng": -31.634},
			{"lat": -80.474, "lng": -31.634},
			{"lat": -80.474, "lng": -28.355}
		]
	},
    {
		"title": "Terminal",
		"notes": "Gang: Son Of Legacy (SOL)",
		"order": 0,
		"strokecolor": "FF0000",
		"fillcolor": "FF0000",
		"latlngarray": [
			{"lat": -80.331, "lng": 5.081},
			{"lat": -80.331, "lng": 24.856},
			{"lat": -83.149, "lng": 24.856},
			{"lat": -83.149, "lng": 5.081}
		]
	},
    {
		"title": "Cypress Flats",
		"notes": "Gang: Son Of Legacy (SOL)",
		"order": 0,
		"strokecolor": "FF0000",
		"fillcolor": "FF0000",
		"latlngarray": [
			{"lat": -73.949, "lng": 3.019},
			{"lat": -73.949, "lng": 11.931},
			{"lat": -75.432, "lng": 11.931},
			{"lat": -75.432, "lng": 15.408},
			{"lat": -80.331, "lng": 15.408},
			{"lat": -80.331, "lng": -0.351},
			{"lat": -76.274, "lng": -0.351},
			{"lat": -76.274, "lng": 3.019}
		]
	},
    {
		"title": "El Burro Heights",
		"notes": "Gang: Son Of Legacy",
		"order": 0,
		"strokecolor": "FF0000",
		"fillcolor": "FF0000",
		"latlngarray": [
			{"lat": -71.216, "lng": 17.418},
			{"lat": -71.216, "lng": 28.121},
			{"lat": -68.828, "lng": 28.121},
			{"lat": -68.828, "lng": 33.195},
			{"lat": -66.859, "lng": 33.195},
			{"lat": -66.859, "lng": 41.787},
			{"lat": -72.675, "lng": 41.787},
			{"lat": -72.675, "lng": 36.323},
			{"lat": -80.331, "lng": 36.323},
			{"lat": -80.331, "lng": 15.408},
			{"lat": -76.077, "lng": 15.408},
			{"lat": -76.077, "lng": 28.121},
			{"lat": -75.432, "lng": 28.121},
			{"lat": -75.432, "lng": 17.418}
		]
	},
    {
		"title": "Rancho",
		"notes": "Gang: Ballas",
		"order": 0,
		"strokecolor": "800080",
		"fillcolor": "800080",
		"latlngarray": [
			{"lat": -71.551, "lng": -4.542},
			{"lat": -71.551, "lng": -0.351},
			{"lat": -72.458, "lng": -0.351},
			{"lat": -72.458, "lng": 3.019},
			{"lat": -76.274, "lng": 3.019},
			{"lat": -76.274, "lng": -0.351},
			{"lat": -77.248, "lng": -0.351},
			{"lat": -77.248, "lng": -11.339},
			{"lat": -76.293, "lng": -11.339},
			{"lat": -76.293, "lng": -8.449},
			{"lat": -74.379, "lng": -8.449},
			{"lat": -74.379, "lng": -7.091},
			{"lat": -73.172, "lng": -7.091},
			{"lat": -73.172, "lng": -4.542}
		]
	},
    {
		"title": "Davis",
		"notes": "Gang: Ballas",
		"order": 0,
		"strokecolor": "800080",
		"fillcolor": "800080",
		"latlngarray": [
			{"lat": -71.551, "lng": -12.272},
			{"lat": -71.551, "lng": -4.542},
			{"lat": -73.172, "lng": -4.542},
			{"lat": -73.172, "lng": -7.091},
			{"lat": -74.379, "lng": -7.091},
			{"lat": -74.379, "lng": -8.449},
			{"lat": -76.293, "lng": -8.449},
			{"lat": -76.293, "lng": -18.923},
			{"lat": -74.359, "lng": -18.923},
			{"lat": -74.359, "lng": -16.751},
			{"lat": -73.862, "lng": -16.751},
			{"lat": -73.862, "lng": -12.272}
		]
	},
    {
		"title": "Strawberry",
		"notes": "Gang: The Lost MC",
		"order": 0,
		"strokecolor": "666362",
		"fillcolor": "666362",
		"latlngarray": [
			{"lat": -68.915, "lng": -26.659},
			{"lat": -68.915, "lng": -0.351},
			{"lat": -71.551, "lng": -0.351},
			{"lat": -71.551, "lng": -12.272},
			{"lat": -73.862, "lng": -12.272},
			{"lat": -73.862, "lng": -16.751},
			{"lat": -71.549, "lng": -16.751},
			{"lat": -71.549, "lng": -26.659}
		]
	},
    {
		"title": "Pillbox Hill",
		"notes": "Gang: The Lost MC",
		"order": 0,
		"strokecolor": "666362",
		"fillcolor": "666362",
		"latlngarray": [
			{"lat": -63.921, "lng": -25.245},
			{"lat": -63.921, "lng": -22.826},
			{"lat": -61.903, "lng": -22.826},
			{"lat": -61.903, "lng": -6.646},
			{"lat": -65.788, "lng": -6.646},
			{"lat": -65.788, "lng": -7.324},
			{"lat": -65.381, "lng": -7.324},
			{"lat": -65.381, "lng": -10.994},
			{"lat": -67.321, "lng": -10.994},
			{"lat": -67.321, "lng": -9.105},
			{"lat": -68.915, "lng": -9.105},
			{"lat": -68.915, "lng": -25.245}
		]
	},
    {
		"title": "Textile City",
		"notes": "Gang: The Lost MC",
		"order": 0,
		"strokecolor": "666362",
		"fillcolor": "666362",
		"latlngarray": [
			{"lat": -61.903, "lng": -6.646},
			{"lat": -61.903, "lng": -0.351},
			{"lat": -65.788, "lng": -0.351},
			{"lat": -65.788, "lng": -6.646}
		]
	},
    {
		"title": "Murrieta Heights",
		"notes": "Gang: Son Of Legacy (SOL)",
		"order": 0,
		"strokecolor": "FF0000",
		"fillcolor": "FF0000",
		"latlngarray": [
			{"lat": -65.079, "lng": 10.917},
			{"lat": -65.079, "lng": 25.338},
			{"lat": -67.321, "lng": 25.338},
			{"lat": -67.321, "lng": 28.121},
			{"lat": -71.216, "lng": 28.121},
			{"lat": -71.216, "lng": 11.942},
			{"lat": -67.321, "lng": 11.942},
			{"lat": -67.321, "lng": 10.917}
		]
	},
    {
		"title": "Mirror Park",
		"notes": "Gang: Son Of Legacy (SOL)",
		"order": 0,
		"strokecolor": "FF0000",
		"fillcolor": "FF0000",
		"latlngarray": [
			{"lat": -57.669, "lng": 10.272},
			{"lat": -57.669, "lng": 25.338},
			{"lat": -65.079, "lng": 25.338},
			{"lat": -65.079, "lng": 10.272}
		]
	},
    {
		"title": "East Vinewood",
		"notes": "Gang: Son Of Legacy (SOL)",
		"order": 0,
		"strokecolor": "FF0000",
		"fillcolor": "FF0000",
		"latlngarray": [
			{"lat": -53.621, "lng": 5.168},
			{"lat": -53.621, "lng": 12.642},
			{"lat": -54.223, "lng": 12.642},
			{"lat": -54.223, "lng": 25.338},
			{"lat": -57.669, "lng": 25.338},
			{"lat": -57.669, "lng": 10.272},
			{"lat": -61.051, "lng": 10.272},
			{"lat": -61.051, "lng": 2.537},
			{"lat": -56.469, "lng": 2.537},
			{"lat": -56.469, "lng": 5.168}
		]
	},
    {
		"title": "Downtown Vinewood",
		"notes": "Gang: Son Of Legacy (SOL)",
		"order": 0,
		"strokecolor": "FF0000",
		"fillcolor": "FF0000",
		"latlngarray": [
			{"lat": -44.544, "lng": -13.503},
			{"lat": -44.544, "lng": 5.168},
			{"lat": -53.373, "lng": 5.168},
			{"lat": -53.373, "lng": -13.503}
		]
	},
    {
		"title": "West Vinewood",
		"notes": "Gang: Son Of Legacy (SOL)",
		"order": 0,
		"strokecolor": "FF0000",
		"fillcolor": "FF0000",
		"latlngarray": [
			{"lat": -44.544, "lng": -36.553},
			{"lat": -44.544, "lng": -13.503},
			{"lat": -53.373, "lng": -13.503},
			{"lat": -53.373, "lng": -22.055},
			{"lat": -52.775, "lng": -22.055},
			{"lat": -52.775, "lng": -36.553}
		]
	},
    {
		"title": "Del Perro",
		"notes": "Gang: The Lost MC",
		"order": 0,
		"strokecolor": "666362",
		"fillcolor": "666362",
		"latlngarray": [
			{"lat": -59.524, "lng": -69.248},
			{"lat": -59.524, "lng": -52.526},
			{"lat": -61.552, "lng": -52.526},
			{"lat": -61.552, "lng": -51.549},
			{"lat": -62.536, "lng": -51.549},
			{"lat": -62.536, "lng": -47.535},
			{"lat": -63.832, "lng": -47.535},
			{"lat": -63.832, "lng": -48.911},
			{"lat": -65.409, "lng": -48.911},
			{"lat": -65.409, "lng": -51.605},
			{"lat": -66.732, "lng": -51.605},
			{"lat": -66.732, "lng": -54.455},
			{"lat": -65.687, "lng": -54.455},
			{"lat": -65.687, "lng": -57.469},
			{"lat": -65.085, "lng": -57.469},
			{"lat": -65.085, "lng": -63.485},
			{"lat": -64.649, "lng": -63.485},
			{"lat": -64.649, "lng": -65.401},
			{"lat": -63.258, "lng": -65.401},
			{"lat": -63.248, "lng": -69.248}
		]
	},
    {
		"title": "Vespucci Canals",
		"notes": "Gang: The Lost MC",
		"order": 0,
		"strokecolor": "666362",
		"fillcolor": "666362",
		"latlngarray": [
			{"lat": -63.832, "lng": -48.911},
			{"lat": -63.832, "lng": -41.994},
			{"lat": -66.147, "lng": -41.994},
			{"lat": -66.147, "lng": -38.469},
			{"lat": -67.401, "lng": -38.469},
			{"lat": -67.401, "lng": -37.381},
			{"lat": -69.469, "lng": -37.381},
			{"lat": -69.469, "lng": -46.797},
			{"lat": -71.543, "lng": -46.797},
			{"lat": -71.543, "lng": -49.708},
			{"lat": -70.169, "lng": -49.708},
			{"lat": -70.169, "lng": -50.669},
			{"lat": -69.059, "lng": -50.669},
			{"lat": -69.059, "lng": -52.101},
			{"lat": -68.012, "lng": -52.101},
			{"lat": -68.012, "lng": -53.182},
			{"lat": -66.732, "lng": -53.182},
			{"lat": -66.732, "lng": -51.605},
			{"lat": -65.409, "lng": -51.605},
			{"lat": -65.409, "lng": -48.911}
		]
	},
    {
		"title": "Vespucci Beach",
		"notes": "Gang: The Lost MC",
		"order": 0,
		"strokecolor": "666362",
		"fillcolor": "666362",
		"latlngarray": [
			{"lat": -66.732, "lng": -55.611},
			{"lat": -66.732, "lng": -53.182},
			{"lat": -70.169, "lng": -53.182},
			{"lat": -70.169, "lng": -52.101},
			{"lat": -71.169, "lng": -52.101},
			{"lat": -71.169, "lng": -50.865},
			{"lat": -71.543, "lng": -50.865},
			{"lat": -71.543, "lng": -48.545},
			{"lat": -72.664, "lng": -48.545},
			{"lat": -72.664, "lng": -46.421},
			{"lat": -75.942, "lng": -46.421},
			{"lat": -75.942, "lng": -48.334},
			{"lat": -74.731, "lng": -48.334},
			{"lat": -74.731, "lng": -51.623},
			{"lat": -74.413, "lng": -51.623},
			{"lat": -74.413, "lng": -52.189},
			{"lat": -74.298, "lng": -52.189},
			{"lat": -74.298, "lng": -52.823},
			{"lat": -73.859, "lng": -52.823},
			{"lat": -73.859, "lng": -53.403},
			{"lat": -73.691, "lng": -53.403},
			{"lat": -73.691, "lng": -53.826},
			{"lat": -73.618, "lng": -53.826},
			{"lat": -73.618, "lng": -54.038},
			{"lat": -73.242, "lng": -54.038},
			{"lat": -73.242, "lng": -54.767},
			{"lat": -73.136, "lng": -54.767},
			{"lat": -73.136, "lng": -55.328},
			{"lat": -72.728, "lng": -55.328},
			{"lat": -72.728, "lng": -56.061},
			{"lat": -72.389, "lng": -56.061},
			{"lat": -72.389, "lng": -56.611},
			{"lat": -71.953, "lng": -56.611},
			{"lat": -71.953, "lng": -57.061},
			{"lat": -71.307, "lng": -57.061},
			{"lat": -71.307, "lng": -58.075},
			{"lat": -70.326, "lng": -58.075},
			{"lat": -70.326, "lng": -58.995},
			{"lat": -69.821, "lng": -58.995},
			{"lat": -69.821, "lng": -59.357},
			{"lat": -69.649, "lng": -59.357},
			{"lat": -69.649, "lng": -59.807},
			{"lat": -69.481, "lng": -59.807},
			{"lat": -69.481, "lng": -60.385},
			{"lat": -69.346, "lng": -60.385},
			{"lat": -69.346, "lng": -60.797},
			{"lat": -68.877, "lng": -60.797},
			{"lat": -68.877, "lng": -57.464},
			{"lat": -68.006, "lng": -57.464},
			{"lat": -68.006, "lng": -55.611}
		]
	},
    {
		"title": "Vinewood Hills",
		"notes": "Gang: The Lost MC",
		"order": 0,
		"strokecolor": "666362",
		"fillcolor": "666362",
		"latlngarray": [
			{"lat": -24.322, "lng": -57.704},
			{"lat": -24.322, "lng": -52.748},
			{"lat": -9.799, "lng": -52.748},
			{"lat": -9.799, "lng": -41.982},
			{"lat": -13.812, "lng": -41.982},
			{"lat": -13.812, "lng": 24.177},
			{"lat": -23.505, "lng": 24.177},
			{"lat": -23.505, "lng": 35.382},
			{"lat": -36.399, "lng": 35.382},
			{"lat": -36.399, "lng": 29.802},
			{"lat": -41.906, "lng": 29.802},
			{"lat": -41.906, "lng": 24.205},
			{"lat": -44.538, "lng": 24.205},
			{"lat": -44.538, "lng": 20.292},
			{"lat": -45.424, "lng": 20.292},
			{"lat": -45.424, "lng": 19.299},
			{"lat": -45.739, "lng": 19.299},
			{"lat": -45.739, "lng": 18.585},
			{"lat": -46.818, "lng": 18.585},
			{"lat": -46.818, "lng": 17.277},
			{"lat": -47.693, "lng": 17.277},
			{"lat": -47.693, "lng": 15.535},
			{"lat": -48.099, "lng": 15.535},
			{"lat": -48.099, "lng": 14.542},
			{"lat": -49.521, "lng": 14.542},
			{"lat": -49.521, "lng": 12.642},
			{"lat": -53.621, "lng": 12.642},
			{"lat": -53.621, "lng": 5.168},
			{"lat": -44.544, "lng": 5.168},
			{"lat": -44.544, "lng": -72.862},
			{"lat": -40.431, "lng": -72.862},
			{"lat": -40.431, "lng": -57.704}
		]
	},
    {
		"title": "Tongva Hills",
		"notes": "Gang: The Lost MC",
		"order": 0,
		"strokecolor": "666362",
		"fillcolor": "666362",
		"latlngarray": [
			{"lat": 4.621, "lng": -82.503},
			{"lat": 4.621, "lng": -60.391},
			{"lat": -24.322, "lng": -60.391},
			{"lat": -24.322, "lng": -72.862},
			{"lat": -16.939, "lng": -72.862},
			{"lat": -16.939, "lng": -105.745},
			{"lat": -4.144, "lng": -105.745},
			{"lat": -4.144, "lng": -92.058},
			{"lat": 1.475, "lng": -92.058},
			{"lat": 1.475, "lng": -82.503}
		]
	},
    {
		"title": "Harmony",
		"notes": "Gang: Son Of Legacy (SOL)",
		"order": 0,
		"strokecolor": "FF0000",
		"fillcolor": "FF0000",
		"latlngarray": [
			{"lat": 17.381, "lng": -10.277},
			{"lat": 17.381, "lng": 5.082},
			{"lat": 9.774, "lng": 5.082},
			{"lat": 9.774, "lng": -10.277}
		]
	},
    {
		"title": "Sandy Shores",
		"notes": "Gang: Son Of Legacy (SOL)",
		"order": 0,
		"strokecolor": "FF0000",
		"fillcolor": "FF0000",
		"latlngarray": [
			{"lat": 47.476, "lng": 55.025},
			{"lat": 47.476, "lng": 66.426},
			{"lat": 37.178, "lng": 66.426},
			{"lat": 37.178, "lng": 63.196},
			{"lat": 30.873, "lng": 63.196},
			{"lat": 30.873, "lng": 47.039},
			{"lat": 34.859, "lng": 47.039},
			{"lat": 34.859, "lng": 22.749},
			{"lat": 46.905, "lng": 22.749},
			{"lat": 46.905, "lng": 47.039},
			{"lat": 43.085, "lng": 47.039},
			{"lat": 43.085, "lng": 55.025}
		]
	},
    {
		"title": "Stab City",
		"notes": "Gang: xxx",
		"order": 0,
		"strokecolor": "F88379",
		"fillcolor": "F88379",
		"latlngarray": [
			{"lat": 43.567, "lng": -17.457},
			{"lat": 43.567, "lng": -7.794},
			{"lat": 38.702, "lng": -7.794},
			{"lat": 38.702, "lng": -10.315},
			{"lat": 36.751, "lng": -10.315},
			{"lat": 36.751, "lng": -14.371},
			{"lat": 38.699, "lng": -14.371},
			{"lat": 38.699, "lng": -17.457}
		]
	},
    {
		"title": "Grapeseed",
		"notes": "Gang: Son Of Legacy (SOL)",
		"order": 0,
		"strokecolor": "FF0000",
		"fillcolor": "FF0000",
		"latlngarray": [
			{"lat": 66.433, "lng": 31.612},
			{"lat": 66.433, "lng": 57.589},
			{"lat": 64.831, "lng": 57.589},
			{"lat": 64.831, "lng": 59.269},
			{"lat": 60.018, "lng": 59.269},
			{"lat": 60.018, "lng": 61.379},
			{"lat": 54.337, "lng": 61.379},
			{"lat": 54.337, "lng": 64.239},
			{"lat": 47.476, "lng": 64.239},
			{"lat": 47.476, "lng": 55.025},
			{"lat": 56.536, "lng": 55.025},
			{"lat": 56.536, "lng": 31.612}
		]
	},
    {
		"title": "Chiliad Mountain State Wilderness",
		"notes": "Gang: Son Of Legacy (SOL)",
		"order": 0,
		"strokecolor": "FF0000",
		"fillcolor": "FF0000",
		"latlngarray": [
			{"lat": 67.153, "lng": -55.521},
			{"lat": 67.153, "lng": -47.789},
			{"lat": 67.432, "lng": -47.789},
			{"lat": 67.432, "lng": -42.879},
			{"lat": 66.288, "lng": -42.879},
			{"lat": 66.288, "lng": -23.614},
			{"lat": 56.639, "lng": -23.614},
			{"lat": 56.639, "lng": -68.285},
			{"lat": 57.887, "lng": -68.285},
			{"lat": 57.887, "lng": -65.343},
			{"lat": 58.756, "lng": -65.343},
			{"lat": 58.756, "lng": -66.735},
			{"lat": 59.277, "lng": -66.735},
			{"lat": 59.277, "lng": -70.564},
			{"lat": 64.636, "lng": -70.564},
			{"lat": 64.636, "lng": -55.521}
		]
	},
    {
		"title": "Paleto Forest",
		"notes": "Gang: Son Of Legacy (SOL)",
		"order": 0,
		"strokecolor": "FF0000",
		"fillcolor": "FF0000",
		"latlngarray": [
			{"lat": 75.891, "lng": -44.515},
			{"lat": 75.891, "lng": -39.607},
			{"lat": 74.779, "lng": -39.607},
			{"lat": 74.779, "lng": -28.799},
			{"lat": 73.611, "lng": -28.799},
			{"lat": 73.611, "lng": -16.081},
			{"lat": 67.432, "lng": -16.081},
			{"lat": 67.432, "lng": -47.789},
			{"lat": 68.624, "lng": -47.789},
			{"lat": 68.624, "lng": -41.177},
			{"lat": 70.278, "lng": -41.177},
			{"lat": 70.278, "lng": -40.477},
			{"lat": 73.214, "lng": -40.477},
			{"lat": 73.214, "lng": -43.159},
			{"lat": 74.785, "lng": -43.159},
			{"lat": 74.785, "lng": -44.515}
		]
	},
    {
		"title": "Paleto Bay",
		"notes": "Gang: Son Of Legacy (SOL)",
		"order": 0,
		"strokecolor": "FF0000",
		"fillcolor": "FF0000",
		"latlngarray": [
			{"lat": 80.844, "lng": -16.059},
			{"lat": 80.844, "lng": -9.234},
			{"lat": 80.361, "lng": -9.234},
			{"lat": 80.361, "lng": -6.935},
			{"lat": 80.025, "lng": -6.935},
			{"lat": 80.025, "lng": -5.238},
			{"lat": 79.787, "lng": -5.238},
			{"lat": 79.787, "lng": -3.688},
			{"lat": 79.525, "lng": -3.688},
			{"lat": 79.525, "lng": -2.432},
			{"lat": 79.215, "lng": -2.432},
			{"lat": 79.215, "lng": -1.224},
			{"lat": 78.911, "lng": -1.224},
			{"lat": 78.911, "lng": 0.803},
			{"lat": 78.685, "lng": 0.803},
			{"lat": 78.685, "lng": 2.943},
			{"lat": 77.904, "lng": 2.943},
			{"lat": 77.904, "lng": 0.099},
			{"lat": 77.322, "lng": 0.099},
			{"lat": 77.322, "lng": -8.771},
			{"lat": 76.611, "lng": -8.771},
			{"lat": 76.611, "lng": -13.039},
			{"lat": 75.101, "lng": -13.039},
			{"lat": 75.101, "lng": -16.081},
			{"lat": 73.611, "lng": -16.081},
			{"lat": 73.611, "lng": -28.799},
			{"lat": 74.779, "lng": -28.799},
			{"lat": 74.779, "lng": -34.591},
			{"lat": 75.751, "lng": -34.591},
			{"lat": 75.751, "lng": -32.277},
			{"lat": 77.071, "lng": -32.277},
			{"lat": 77.071, "lng": -25.198},
			{"lat": 77.921, "lng": -25.198},
			{"lat": 77.921, "lng": -20.819},
			{"lat": 78.451, "lng": -20.819},
			{"lat": 78.451, "lng": -19.665},
			{"lat": 78.688, "lng": -19.665},
			{"lat": 78.688, "lng": -18.119},
			{"lat": 79.422, "lng": -18.119},
			{"lat": 79.426, "lng": -16.059}
		]
	},
    {
		"title": "Davis Quartz",
		"notes": "Gang: Ballas",
		"order": 0,
		"strokecolor": "800080",
		"fillcolor": "800080",
		"latlngarray": [
			{"lat": 24.498, "lng": 66.949},
			{"lat": 24.498, "lng": 75.042},
			{"lat": 14.131, "lng": 75.042},
			{"lat": 14.131, "lng": 81.347},
			{"lat": 8.438, "lng": 81.347},
			{"lat": 8.438, "lng": 59.213},
			{"lat": 14.114, "lng": 59.213},
			{"lat": 14.114, "lng": 58.626},
			{"lat": 21.895, "lng": 58.626},
			{"lat": 21.895, "lng": 60.785},
			{"lat": 24.175, "lng": 60.785},
			{"lat": 24.175, "lng": 66.949}
		]
	},
    {
		"title": "Hawick",
		"notes": "Gang: Jhola Gang",
		"order": 0,
		"strokecolor": "895129",
		"fillcolor": "895129",
		"latlngarray": [
			{"lat": -53.373, "lng": -16.248},
			{"lat": -53.373, "lng": 5.168},
			{"lat": -56.469, "lng": 5.168},
			{"lat": -56.469, "lng": -16.248}
		]
	},
    {
		"title": "Procopio Beach",
		"notes": "Gang: Son Of Legacy (SOL)",
		"order": 0,
		"strokecolor": "FF0000",
		"fillcolor": "FF0000",
		"latlngarray": [
			{"lat": 78.325, "lng": 2.943},
			{"lat": 78.325, "lng": 30.151},
			{"lat": 77.678, "lng": 30.151},
			{"lat": 77.678, "lng": 0.099},
			{"lat": 77.903, "lng": 0.099},
			{"lat": 77.905, "lng": 2.943}
		]
	}
]
